[
  {
    "anonymous": false,
    "inputs": [
      {
        "indexed": true,
        "internalType": "bytes32",
        "name": "transactionId",
        "type": "bytes32"
      },
      {
        "indexed": false,
        "internalType": "string",
        "name": "integrator",
        "type": "string"
      },
      {
        "indexed": false,
        "internalType": "string",
        "name": "referrer",
        "type": "string"
      },
      {
        "indexed": false,
        "internalType": "address",
        "name": "receiver",
        "type": "address"
      },
      {
        "indexed": false,
        "internalType": "address",
        "name": "fromAssetId",
        "type": "address"
      },
      {
        "indexed": false,
        "internalType": "address",
        "name": "toAssetId",
        "type": "address"
      },
      {
        "indexed": false,
        "internalType": "uint256",
        "name": "fromAmount",
        "type": "uint256"
      },
      {
        "indexed": false,
        "internalType": "uint256",
        "name": "toAmount",
        "type": "uint256"
      }
    ],
    "name": "LiFiGenericSwapCompleted",
    "type": "event"
  }
]
